hesseflux/__init__.py
hesseflux/_version.py
hesseflux/gapfill.py
hesseflux/madspikes.py
hesseflux/nee2gpp.py
hesseflux/ustarfilter.py
hesseflux-5.0.dist-info/LICENSE
hesseflux-5.0.dist-info/METADATA
hesseflux-5.0.dist-info/WHEEL
hesseflux-5.0.dist-info/top_level.txt
hesseflux-5.0.dist-info/RECORD
